aiohdfs/errors.py
aiohdfs/operations.py
aiohdfs/__init__.py
aiohdfs-0.1.3.dev1.dist-info/DESCRIPTION.rst
aiohdfs-0.1.3.dev1.dist-info/METADATA
aiohdfs-0.1.3.dev1.dist-info/metadata.json
aiohdfs-0.1.3.dev1.dist-info/pbr.json
aiohdfs-0.1.3.dev1.dist-info/RECORD
aiohdfs-0.1.3.dev1.dist-info/top_level.txt
aiohdfs-0.1.3.dev1.dist-info/WHEEL
