Metadata-Version: 2.0
Name: aiohdfs
Version: 0.1.3.dev1
Summary: UNKNOWN
Home-page: https://github.com/RiverlandReply/aiohdfs
Author: Artyom Topchyan
Author-email: a.topchyan@reply.de
License: UNKNOWN
Platform: UNKNOWN
Requires-Dist: asyncio
Requires-Dist: aiohttp
